pana.py
pana-0.2.1.data/scripts/pana.py
pana-0.2.1.dist-info/LICENSE
pana-0.2.1.dist-info/METADATA
pana-0.2.1.dist-info/WHEEL
pana-0.2.1.dist-info/entry_points.txt
pana-0.2.1.dist-info/top_level.txt
pana-0.2.1.dist-info/RECORD
