Metadata-Version: 2.1
Name: pana
Version: 0.2.1
Summary: Pana is a CLI and module built to check if a package name or username is available from common package managers.
Home-page: https://github.com/battleoverflow/pana
Author: battleoverflow
Classifier: Programming Language :: Python :: 3
Classifier: License :: OSI Approved :: BSD License
Classifier: Operating System :: OS Independent
Requires-Python: >=3.6
License-File: LICENSE
Requires-Dist: requests
Requires-Dist: colorama
